csankey/__init__.py
csankey/_csankey.cp38-win_amd64.pyd
csankey-0.6.7.data/scripts/sankey.exe
csankey-0.6.7.dist-info/LICENSE
csankey-0.6.7.dist-info/METADATA
csankey-0.6.7.dist-info/WHEEL
csankey-0.6.7.dist-info/top_level.txt
csankey-0.6.7.dist-info/RECORD
