Metadata-Version: 2.1
Name: csankey
Version: 0.6.7
Summary: csankey description
Home-page: https://github.com/kirin123kirin/csankey
Author: kirin123kirin
License: MIT
Keywords: sankey,d3.js
Platform: UNKNOWN
Classifier: Programming Language :: Python :: 3
Classifier: Programming Language :: Python :: 3.6
Classifier: Programming Language :: Python :: 3.7
Classifier: Programming Language :: Python :: 3.8
Classifier: Programming Language :: Python :: 3.9
Classifier: Programming Language :: Python :: 3.10
Classifier: License :: OSI Approved :: MIT License
License-File: LICENSE
Requires-Dist: setuptools (>=42)
Requires-Dist: wheel
Requires-Dist: scikit-build (>=0.12)
Requires-Dist: cmake (>=3.18)
Provides-Extra: test
Requires-Dist: pytest ; extra == 'test'
Requires-Dist: pytest-cov ; extra == 'test'
Requires-Dist: psutil ; extra == 'test'
Requires-Dist: lxml ; extra == 'test'
